{
  "id": "9334a3c4-ab47-4d9d-aaba-e1417cfdfaed",
  "prevId": "00000000-0000-0000-0000-000000000000",
  "version": "5",
  "dialect": "pg",
  "tables": {
    "items": {
      "name": "items",
      "schema": "",
      "columns": {
        "id": {
          "name": "id",
          "type": "serial",
          "primaryKey": true,
          "notNull": true
        },
        "name": {
          "name": "name",
          "type": "varchar(256)",
          "primaryKey": false,
          "notNull": false
        }
      },
      "indexes": {},
      "foreignKeys": {},
      "compositePrimaryKeys": {},
      "uniqueConstraints": {}
    }
  },
  "enums": {},
  "schemas": {},
  "_meta": {
    "schemas": {},
    "tables": {},
    "columns": {}
  }
}